<?xml version="1.0" encoding="UTF-8"?>
<gpx creator="OSRM Routing Engine" version="1.1" xmlns="http://www.topografix.com/GPX/1/1" xmlns:xsi="http://www.w3.org/2001/XMLSchema-instance" xsi:schemaLocation="http://www.topografix.com/GPX/1/1 gpx.xsd">
    <metadata>
        <copyright author="Project OSRM">
            <license>Data (c) OpenStreetMap contributors (ODbL)</license>
        </copyright>
    </metadata>
    <rte>
        <rtept lat="41.981512" lon="21.490673"></rtept>
        <rtept lat="41.981253" lon="21.490282"></rtept>
        <rtept lat="41.980671" lon="21.489326"></rtept>
        <rtept lat="41.980419" lon="21.488952"></rtept>
        <rtept lat="41.980114" lon="21.488453"></rtept>
        <rtept lat="41.979630" lon="21.487623"></rtept>
        <rtept lat="41.979386" lon="21.487229"></rtept>
        <rtept lat="41.979260" lon="21.487011"></rtept>
        <rtept lat="41.978986" lon="21.486565"></rtept>
        <rtept lat="41.978109" lon="21.485170"></rtept>
        <rtept lat="41.978060" lon="21.485090"></rtept>
        <rtept lat="41.977215" lon="21.483677"></rtept>
        <rtept lat="41.976782" lon="21.482978"></rtept>
        <rtept lat="41.976248" lon="21.482125"></rtept>
        <rtept lat="41.975798" lon="21.481415"></rtept>
        <rtept lat="41.975615" lon="21.481128"></rtept>
        <rtept lat="41.975047" lon="21.480216"></rtept>
        <rtept lat="41.974701" lon="21.479622"></rtept>
        <rtept lat="41.974312" lon="21.479077"></rtept>
        <rtept lat="41.974496" lon="21.478670"></rtept>
        <rtept lat="41.973929" lon="21.478201"></rtept>
        <rtept lat="41.973729" lon="21.478035"></rtept>
        <rtept lat="41.973493" lon="21.477958"></rtept>
        <rtept lat="41.972835" lon="21.477914"></rtept>
        <rtept lat="41.972279" lon="21.477869"></rtept>
        <rtept lat="41.971736" lon="21.477766"></rtept>
        <rtept lat="41.971528" lon="21.477628"></rtept>
        <rtept lat="41.971314" lon="21.477442"></rtept>
        <rtept lat="41.972911" lon="21.474045"></rtept>
        <rtept lat="41.973716" lon="21.472332"></rtept>
        <rtept lat="41.974174" lon="21.471349"></rtept>
        <rtept lat="41.974375" lon="21.470918"></rtept>
        <rtept lat="41.974882" lon="21.469829"></rtept>
        <rtept lat="41.975912" lon="21.467620"></rtept>
        <rtept lat="41.976793" lon="21.465628"></rtept>
        <rtept lat="41.977035" lon="21.465114"></rtept>
        <rtept lat="41.977231" lon="21.464699"></rtept>
        <rtept lat="41.977285" lon="21.464551"></rtept>
        <rtept lat="41.977325" lon="21.464439"></rtept>
        <rtept lat="41.977508" lon="21.464051"></rtept>
        <rtept lat="41.978031" lon="21.462941"></rtept>
        <rtept lat="41.978098" lon="21.462797"></rtept>
        <rtept lat="41.978473" lon="21.461989"></rtept>
        <rtept lat="41.978504" lon="21.461922"></rtept>
        <rtept lat="41.979282" lon="21.460242"></rtept>
        <rtept lat="41.982131" lon="21.454079"></rtept>
        <rtept lat="41.983220" lon="21.451706"></rtept>
        <rtept lat="41.983599" lon="21.450906"></rtept>
        <rtept lat="41.984476" lon="21.449088"></rtept>
        <rtept lat="41.985001" lon="21.447918"></rtept>
        <rtept lat="41.985550" lon="21.446723"></rtept>
        <rtept lat="41.985909" lon="21.445943"></rtept>
        <rtept lat="41.986504" lon="21.444687"></rtept>
        <rtept lat="41.987139" lon="21.443262"></rtept>
        <rtept lat="41.987581" lon="21.442300"></rtept>
        <rtept lat="41.987749" lon="21.441940"></rtept>
        <rtept lat="41.987983" lon="21.441444"></rtept>
        <rtept lat="41.988156" lon="21.441078"></rtept>
        <rtept lat="41.988324" lon="21.441348"></rtept>
        <rtept lat="41.988555" lon="21.441724"></rtept>
        <rtept lat="41.989001" lon="21.442377"></rtept>
        <rtept lat="41.989576" lon="21.443029"></rtept>
        <rtept lat="41.989950" lon="21.443438"></rtept>
        <rtept lat="41.990196" lon="21.443706"></rtept>
        <rtept lat="41.990359" lon="21.443883"></rtept>
        <rtept lat="41.990573" lon="21.444118"></rtept>
        <rtept lat="41.990647" lon="21.444198"></rtept>
        <rtept lat="41.990679" lon="21.444234"></rtept>
        <rtept lat="41.990727" lon="21.444286"></rtept>
        <rtept lat="41.991263" lon="21.444871"></rtept>
        <rtept lat="41.991428" lon="21.445051"></rtept>
        <rtept lat="41.991515" lon="21.445144"></rtept>
        <rtept lat="41.991630" lon="21.445269"></rtept>
        <rtept lat="41.991732" lon="21.445381"></rtept>
        <rtept lat="41.992988" lon="21.443336"></rtept>
        <rtept lat="41.993013" lon="21.443295"></rtept>
        <rtept lat="41.993071" lon="21.443201"></rtept>
        <rtept lat="41.993168" lon="21.443041"></rtept>
        <rtept lat="41.994131" lon="21.441451"></rtept>
        <rtept lat="41.994211" lon="21.441232"></rtept>
        <rtept lat="41.994230" lon="21.441088"></rtept>
        <rtept lat="41.994233" lon="21.441010"></rtept>
        <rtept lat="41.994237" lon="21.440903"></rtept>
        <rtept lat="41.994124" lon="21.440745"></rtept>
        <rtept lat="41.993974" lon="21.440704"></rtept>
        <rtept lat="41.993830" lon="21.440652"></rtept>
        <rtept lat="41.993661" lon="21.440562"></rtept>
        <rtept lat="41.993512" lon="21.440451"></rtept>
        <rtept lat="41.993365" lon="21.440308"></rtept>
        <rtept lat="41.993154" lon="21.440042"></rtept>
        <rtept lat="41.992078" lon="21.437893"></rtept>
        <rtept lat="41.991931" lon="21.437593"></rtept>
        <rtept lat="41.990952" lon="21.435637"></rtept>
        <rtept lat="41.990928" lon="21.435511"></rtept>
        <rtept lat="41.990928" lon="21.435364"></rtept>
        <rtept lat="41.990928" lon="21.435251"></rtept>
        <rtept lat="41.990970" lon="21.435117"></rtept>
        <rtept lat="41.991021" lon="21.435012"></rtept>
        <rtept lat="41.991081" lon="21.434904"></rtept>
        <rtept lat="41.992280" lon="21.433917"></rtept>
        <rtept lat="41.992549" lon="21.433693"></rtept>
        <rtept lat="41.992617" lon="21.433638"></rtept>
        <rtept lat="41.992733" lon="21.433544"></rtept>
        <rtept lat="41.992832" lon="21.433761"></rtept>
        <rtept lat="41.992871" lon="21.433850"></rtept>
        <rtept lat="41.993162" lon="21.434507"></rtept>
        <rtept lat="41.993538" lon="21.435346"></rtept>
        <rtept lat="41.993624" lon="21.435545"></rtept>
        <rtept lat="41.993790" lon="21.435927"></rtept>
        <rtept lat="41.993883" lon="21.436130"></rtept>
        <rtept lat="41.993942" lon="21.436238"></rtept>
        <rtept lat="41.994117" lon="21.436547"></rtept>
        <rtept lat="41.994171" lon="21.436614"></rtept>
        <rtept lat="41.994265" lon="21.436673"></rtept>
        <rtept lat="41.994711" lon="21.436918"></rtept>
        <rtept lat="41.994951" lon="21.437048"></rtept>
        <rtept lat="41.995566" lon="21.437381"></rtept>
        <rtept lat="41.995739" lon="21.437474"></rtept>
        <rtept lat="41.995886" lon="21.437545"></rtept>
        <rtept lat="41.996029" lon="21.437615"></rtept>
        <rtept lat="41.996316" lon="21.437741"></rtept>
        <rtept lat="41.996531" lon="21.437827"></rtept>
        <rtept lat="41.996709" lon="21.437885"></rtept>
        <rtept lat="41.996840" lon="21.437920"></rtept>
        <rtept lat="41.996938" lon="21.437945"></rtept>
        <rtept lat="41.997007" lon="21.437963"></rtept>
        <rtept lat="41.997088" lon="21.437984"></rtept>
        <rtept lat="41.997628" lon="21.438071"></rtept>
        <rtept lat="41.998064" lon="21.438141"></rtept>
        <rtept lat="41.998474" lon="21.438197"></rtept>
        <rtept lat="41.998625" lon="21.438202"></rtept>
        <rtept lat="41.998661" lon="21.438201"></rtept>
        <rtept lat="41.998796" lon="21.438191"></rtept>
        <rtept lat="41.998778" lon="21.438499"></rtept>
        <rtept lat="41.998750" lon="21.438954"></rtept>
        <rtept lat="41.998704" lon="21.439920"></rtept>
        <rtept lat="41.998697" lon="21.440100"></rtept>
        <rtept lat="41.998687" lon="21.440328"></rtept>
        <rtept lat="41.998680" lon="21.440504"></rtept>
        <rtept lat="41.998785" lon="21.440489"></rtept>
        <rtept lat="41.999125" lon="21.440404"></rtept>
        <rtept lat="41.999399" lon="21.440348"></rtept>
        <rtept lat="42.000496" lon="21.440162"></rtept>
        <rtept lat="42.001478" lon="21.439969"></rtept>
        <rtept lat="42.001980" lon="21.439881"></rtept>
        <rtept lat="42.002557" lon="21.439879"></rtept>
        <rtept lat="42.002909" lon="21.439909"></rtept>
        <rtept lat="42.003031" lon="21.439932"></rtept>
        <rtept lat="42.003620" lon="21.440138"></rtept>
        <rtept lat="42.003717" lon="21.440172"></rtept>
        <rtept lat="42.004263" lon="21.440369"></rtept>
        <rtept lat="42.004407" lon="21.440434"></rtept>
        <rtept lat="42.004656" lon="21.440567"></rtept>
        <rtept lat="42.005201" lon="21.441013"></rtept>
        <rtept lat="42.005232" lon="21.441166"></rtept>
        <rtept lat="42.005194" lon="21.441310"></rtept>
        <rtept lat="42.005139" lon="21.441422"></rtept>
        <rtept lat="42.005035" lon="21.441593"></rtept>
        <rtept lat="42.004782" lon="21.441848"></rtept>
        <rtept lat="42.004640" lon="21.441985"></rtept>
        <rtept lat="42.004541" lon="21.441955"></rtept>
        <rtept lat="42.004431" lon="21.441870"></rtept>
        <rtept lat="42.004429" lon="21.441775"></rtept>
        <rtept lat="42.004738" lon="21.441289"></rtept>
        <rtept lat="42.004944" lon="21.440969"></rtept>
        <rtept lat="42.005292" lon="21.440355"></rtept>
        <rtept lat="42.005630" lon="21.439734"></rtept>
        <rtept lat="42.006198" lon="21.438630"></rtept>
        <rtept lat="42.006485" lon="21.437952"></rtept>
        <rtept lat="42.006868" lon="21.437141"></rtept>
        <rtept lat="42.007212" lon="21.436415"></rtept>
        <rtept lat="42.007275" lon="21.436283"></rtept>
        <rtept lat="42.007801" lon="21.435176"></rtept>
        <rtept lat="42.008117" lon="21.434535"></rtept>
        <rtept lat="42.008682" lon="21.433274"></rtept>
        <rtept lat="42.008796" lon="21.433014"></rtept>
        <rtept lat="42.009311" lon="21.431922"></rtept>
        <rtept lat="42.009870" lon="21.430745"></rtept>
    </rte>
</gpx>